cacheguard/__init__.py
cacheguard/age.py
cacheguard/base_cache.py
cacheguard/key_cache.py
cacheguard/sops.py
cacheguard/text_cache.py
cacheguard-0.3.0.dist-info/METADATA
cacheguard-0.3.0.dist-info/WHEEL
cacheguard-0.3.0.dist-info/licenses/LICENSE
cacheguard-0.3.0.dist-info/RECORD
