Metadata-Version: 2.4
Name: cacheguard
Version: 0.3.0
Summary: A simple, secure Python datastore protected by Sops or Age
Author-email: Michael Buckley <michaelcbuckley@proton.me>
License: MIT
License-File: LICENSE
Requires-Python: >=3.13
